[{"model": "gods", "data": {"name":"Agni","summary":"","title":"God of Fire","pantheon":"Hindu","type":"RangedMagical","class":"Mage","pros":"High Area Damage","difficulty":"Hard","release_date":"May 31 2012","favor":1250,"gems":200,"voicelines":"Agni voicelines","voice_actor":"Scott Freeman","health":360,"health_Growth_Rate":71,"mana":255,"mana_Growth_Rate":45,"speed":350,"speed_Growth_Rate":0,"range":55,"range_Growth_Rate":0,"attack_Sec":0.86,"attack_Sec_Growth_Rate":0.0101,"damage":34,"damage_Growth_Rate":1.5,"damage_Growth_Rate_2":"20% of Magical Power","progression":"None","physical":11,"physical_Growth_Rate":2.6,"magical":30,"magical_Growth_Rate":0,"hp5":7,"hp5_Growth_Rate":0.47,"mp5":4.7,"mp5_Growth_Rate":0.37, "smallimg": "assets/images/god_thumbs/1737.jpg", "physicalprotection": 11, "physicalprotection_Growth_Rate": 2.6, "magicalprotection": 30, "magicalprotection_Growth_Rate": 0}},
{"model": "gods", "data": {"name":"Ah Muzen Cab","summary":"","title":"God of Bees","pantheon":"Mayan","type":"RangedPhysical","class":"Hunter","pros":"High Movement Speed High Attack Speed","difficulty":"Average","release_date":"November 7 2013","favor":5500,"gems":200,"voicelines":"Ah Muzen Cab voicelines","voice_actor":"Jason Liebrecht","health":450,"health_Growth_Rate":73,"mana":230,"mana_Growth_Rate":40,"speed":365,"speed_Growth_Rate":0,"range":55,"range_Growth_Rate":0,"attack_Sec":0.95,"attack_Sec_Growth_Rate":0.017,"damage":38,"damage_Growth_Rate":2.2,"damage_Growth_Rate_2":"100% of Physical Power","progression":"None","physical":12,"physical_Growth_Rate":3,"magical":30,"magical_Growth_Rate":0.9,"hp5":7,"hp5_Growth_Rate":0.71,"mp5":4.4,"mp5_Growth_Rate":0.38, "smallimg": "assets/images/god_thumbs/1956.jpg", "physicalprotection": 12, "physicalprotection_Growth_Rate": 3, "magicalprotection": 30, "magicalprotection_Growth_Rate": 0.9}},
{"model": "gods", "data": {"name":"Ah Puch","summary":"","title":"Horrific God of Decay","pantheon":"Mayan","type":"RangedMagical","class":"Mage","pros":"High Area Damage","difficulty":"Average","release_date":"April 28 2015","favor":5500,"gems":200,"voicelines":"Ah Puch voicelines","voice_actor":"Bruce Carey","health":375,"health_Growth_Rate":70,"mana":265,"mana_Growth_Rate":55,"speed":355,"speed_Growth_Rate":0,"range":55,"range_Growth_Rate":0,"attack_Sec":0.86,"attack_Sec_Growth_Rate":0.0095,"damage":35,"damage_Growth_Rate":1.5,"damage_Growth_Rate_2":"20% of Magical Power","progression":"None","physical":9,"physical_Growth_Rate":2.7,"magical":30,"magical_Growth_Rate":0,"hp5":6,"hp5_Growth_Rate":0.45,"mp5":4.9,"mp5_Growth_Rate":0.42, "smallimg": "assets/images/god_thumbs/2056.jpg", "physicalprotection": 9, "physicalprotection_Growth_Rate": 2.7, "magicalprotection": 30, "magicalprotection_Growth_Rate": 0}},
{"model": "gods", "data": {"name":"Amaterasu","summary":"","title":"The Shining Light","pantheon":"Japanese","type":"MeleePhysical","class":"Warrior","pros":"High Mobility High Area Damage","difficulty":"Average","release_date":"January 12 2016","favor":5500,"gems":200,"voicelines":"Amaterasu voicelines","voice_actor":"Cristina Valenzuela","health":470,"health_Growth_Rate":82,"mana":220,"mana_Growth_Rate":35,"speed":375,"speed_Growth_Rate":0,"range":12,"range_Growth_Rate":0,"attack_Sec":1,"attack_Sec_Growth_Rate":0.012,"damage":39,"damage_Growth_Rate":2,"damage_Growth_Rate_2":"100% of Physical Power","progression":"1/.5/1 damage and swing time","physical":18,"physical_Growth_Rate":3,"magical":30,"magical_Growth_Rate":0.9,"hp5":8,"hp5_Growth_Rate":0.8,"mp5":4.8,"mp5_Growth_Rate":0.4, "smallimg": "assets/images/god_thumbs/Amaterasu_Default_Icon.jpg", "physicalprotection": 18, "physicalprotection_Growth_Rate": 3, "magicalprotection": 30, "magicalprotection_Growth_Rate": 0.9}},
{"model": "gods", "data": {"name":"Anhur","summary":"","title":"Slayer of Enemies","pantheon":"Egyptian","type":"RangedPhysical","class":"Hunter","pros":"High Single Target Damage","difficulty":"Average","release_date":"August 3 2012","favor":5500,"gems":200,"voicelines":"Anhur voicelines","voice_actor":"Christopher Sabat","health":460,"health_Growth_Rate":78,"mana":220,"mana_Growth_Rate":35,"speed":365,"speed_Growth_Rate":0,"range":55,"range_Growth_Rate":0,"attack_Sec":0.9,"attack_Sec_Growth_Rate":0.017,"damage":40,"damage_Growth_Rate":2.5,"damage_Growth_Rate_2":"100% of Physical Power","progression":"None","physical":11,"physical_Growth_Rate":2.8,"magical":30,"magical_Growth_Rate":0.9,"hp5":8,"hp5_Growth_Rate":0.69,"mp5":4.5,"mp5_Growth_Rate":0.32, "smallimg": "assets/images/god_thumbs/1773.jpg", "physicalprotection": 11, "physicalprotection_Growth_Rate": 2.8, "magicalprotection": 30, "magicalprotection_Growth_Rate": 0.9}},
{"model": "gods", "data": {"name":"Anubis","summary":"","title":"God of the Dead","pantheon":"Egyptian","type":"RangedMagical","class":"Mage","pros":"High Area Damage","difficulty":"Easy","release_date":"May 31 2012","favor":5500,"gems":200,"voicelines":"Anubis voicelines","voice_actor":"R. Bruce Elliott","health":350,"health_Growth_Rate":66,"mana":280,"mana_Growth_Rate":58,"speed":350,"speed_Growth_Rate":0,"range":55,"range_Growth_Rate":0,"attack_Sec":0.86,"attack_Sec_Growth_Rate":0.0099,"damage":35,"damage_Growth_Rate":1.5,"damage_Growth_Rate_2":"20% of Magical Power","progression":"None","physical":10,"physical_Growth_Rate":2.5,"magical":30,"magical_Growth_Rate":0,"hp5":7,"hp5_Growth_Rate":0.45,"mp5":4.8,"mp5_Growth_Rate":0.36, "smallimg": "assets/images/god_thumbs/1668.jpg", "physicalprotection": 10, "physicalprotection_Growth_Rate": 2.5, "magicalprotection": 30, "magicalprotection_Growth_Rate": 0}},
{"model": "gods", "data": {"name":"Ao Kuang","summary":"","title":"Dragon King of theEastern Seas","pantheon":"Chinese","type":"MeleeMagical","class":"Mage","pros":"High Single Target Damage","difficulty":"Hard","release_date":"November 19 2014","favor":5500,"gems":200,"voicelines":"Ao Kuang voicelines","voice_actor":"Kaiji Tang","health":400,"health_Growth_Rate":82,"mana":200,"mana_Growth_Rate":36,"speed":375,"speed_Growth_Rate":0,"range":12,"range_Growth_Rate":0,"attack_Sec":1,"attack_Sec_Growth_Rate":0.0195,"damage":35,"damage_Growth_Rate":2.4,"damage_Growth_Rate_2":"20% of Magical Power","progression":"1/0.5/0.5/1x damage1/0.5/0.5/0.5x Speed","physical":12,"physical_Growth_Rate":3,"magical":30,"magical_Growth_Rate":0.9,"hp5":10,"hp5_Growth_Rate":0.7,"mp5":4.5,"mp5_Growth_Rate":0.2, "smallimg": "assets/images/god_thumbs/2034.jpg", "physicalprotection": 12, "physicalprotection_Growth_Rate": 3, "magicalprotection": 30, "magicalprotection_Growth_Rate": 0.9}},
{"model": "gods", "data": {"name":"Aphrodite","summary":"","title":"Goddess of Beauty","pantheon":"Greek","type":"RangedMagical","class":"Mage","pros":"High Sustain","difficulty":"Hard","release_date":"March 13 2013","favor":5500,"gems":200,"voicelines":"Aphrodite voicelines","voice_actor":"Martha Harms","health":355,"health_Growth_Rate":68,"mana":240,"mana_Growth_Rate":43,"speed":355,"speed_Growth_Rate":0,"range":55,"range_Growth_Rate":0,"attack_Sec":0.87,"attack_Sec_Growth_Rate":0.0095,"damage":32,"damage_Growth_Rate":1.45,"damage_Growth_Rate_2":"20% of Magical Power","progression":"None","physical":9,"physical_Growth_Rate":2.7,"magical":30,"magical_Growth_Rate":0,"hp5":6,"hp5_Growth_Rate":0.45,"mp5":4.8,"mp5_Growth_Rate":0.41, "smallimg": "assets/images/god_thumbs/1898.jpg", "physicalprotection": 9, "physicalprotection_Growth_Rate": 2.7, "magicalprotection": 30, "magicalprotection_Growth_Rate": 0}},
{"model": "gods", "data": {"name":"Apollo","summary":"","title":"God of Music","pantheon":"Greek","type":"RangedPhysical","class":"Hunter","pros":"High Mobility","difficulty":"Easy","release_date":"March 28 2013","favor":5500,"gems":200,"voicelines":"Apollo voicelines","voice_actor":"Phil Parsons","health":450,"health_Growth_Rate":77,"mana":225,"mana_Growth_Rate":40,"speed":365,"speed_Growth_Rate":0,"range":55,"range_Growth_Rate":0,"attack_Sec":0.95,"attack_Sec_Growth_Rate":0.017,"damage":40,"damage_Growth_Rate":2.6,"damage_Growth_Rate_2":"100% of Physical Power","progression":"None","physical":12,"physical_Growth_Rate":2.7,"magical":30,"magical_Growth_Rate":0.9,"hp5":8,"hp5_Growth_Rate":0.69,"mp5":4.6,"mp5_Growth_Rate":0.4, "smallimg": "assets/images/god_thumbs/1899.jpg", "physicalprotection": 12, "physicalprotection_Growth_Rate": 2.7, "magicalprotection": 30, "magicalprotection_Growth_Rate": 0.9}},
{"model": "gods", "data": {"name":"Arachne","summary":"","title":"The Weaver","pantheon":"Greek","type":"MeleePhysical","class":"Assassin","pros":"High Single Target Damage Great Jungler","difficulty":"Average","release_date":"May 31 2012","favor":5500,"gems":200,"voicelines":"Arachne voicelines","voice_actor":"Colleen Clinkenbeard","health":445,"health_Growth_Rate":79,"mana":210,"mana_Growth_Rate":41,"speed":375,"speed_Growth_Rate":0,"range":12,"range_Growth_Rate":0,"attack_Sec":1,"attack_Sec_Growth_Rate":0.02,"damage":38,"damage_Growth_Rate":2.2,"damage_Growth_Rate_2":"100% of Physical Power","progression":".5/1/1x","physical":13,"physical_Growth_Rate":3,"magical":30,"magical_Growth_Rate":0.9,"hp5":9,"hp5_Growth_Rate":0.67,"mp5":4.8,"mp5_Growth_Rate":0.46, "smallimg": "assets/images/god_thumbs/standardarachne.jpg", "physicalprotection": 13, "physicalprotection_Growth_Rate": 3, "magicalprotection": 30, "magicalprotection_Growth_Rate": 0.9}},
{"model": "gods", "data": {"name":"Ares","summary":"","title":"God of War","pantheon":"Greek","type":"MeleeMagical","class":"Guardian","pros":"High Crowd Control High Defense","difficulty":"Easy","release_date":"October 4 2012","favor":5500,"gems":200,"voicelines":"Ares voicelines","voice_actor":"Jason Douglas","health":485,"health_Growth_Rate":90,"mana":200,"mana_Growth_Rate":37,"speed":360,"speed_Growth_Rate":0,"range":12,"range_Growth_Rate":0,"attack_Sec":0.9,"attack_Sec_Growth_Rate":0.0125,"damage":38,"damage_Growth_Rate":1.55,"damage_Growth_Rate_2":"20% of Magical Power","progression":"1/.75/1/1.25x damage and swing time","physical":17,"physical_Growth_Rate":3,"magical":30,"magical_Growth_Rate":0.9,"hp5":8,"hp5_Growth_Rate":0.67,"mp5":4.6,"mp5_Growth_Rate":0.42, "smallimg": "assets/images/god_thumbs/1782.jpg", "physicalprotection": 17, "physicalprotection_Growth_Rate": 3, "magicalprotection": 30, "magicalprotection_Growth_Rate": 0.9}},
{"model": "gods", "data": {"name":"Artemis","summary":"","title":"Goddess of the Hunt","pantheon":"Greek","type":"RangedPhysical","class":"Hunter","pros":"High Single Target Damage","difficulty":"Average","release_date":"May 31 2012","favor":575,"gems":200,"voicelines":"Artemis voicelines","voice_actor":"Brina Palencia","health":450,"health_Growth_Rate":72,"mana":205,"mana_Growth_Rate":34,"speed":365,"speed_Growth_Rate":0,"range":55,"range_Growth_Rate":0,"attack_Sec":0.95,"attack_Sec_Growth_Rate":0.014,"damage":35,"damage_Growth_Rate":2.05,"damage_Growth_Rate_2":"100% of Physical Power","progression":"None","physical":12,"physical_Growth_Rate":3,"magical":30,"magical_Growth_Rate":0.9,"hp5":8,"hp5_Growth_Rate":0.68,"mp5":4.4,"mp5_Growth_Rate":0.25, "smallimg": "assets/images/god_thumbs/1748.jpg", "physicalprotection": 12, "physicalprotection_Growth_Rate": 3, "magicalprotection": 30, "magicalprotection_Growth_Rate": 0.9}},
{"model": "gods", "data": {"name":"Athena","summary":"","title":"Goddess of Wisdom","pantheon":"Greek","type":"MeleeMagical","class":"Guardian","pros":"High Crowd Control High Defense","difficulty":"Easy","release_date":"June 5 2013","favor":5500,"gems":200,"voicelines":"Athena voicelines","voice_actor":"Kara Edwards","health":500,"health_Growth_Rate":100,"mana":190,"mana_Growth_Rate":34,"speed":365,"speed_Growth_Rate":0,"range":12,"range_Growth_Rate":0,"attack_Sec":1,"attack_Sec_Growth_Rate":0.012,"damage":35,"damage_Growth_Rate":1.5,"damage_Growth_Rate_2":"20% of Magical Power","progression":"1/1/2x damage and swing time","physical":20,"physical_Growth_Rate":3.2,"magical":30,"magical_Growth_Rate":0.9,"hp5":8,"hp5_Growth_Rate":0.9,"mp5":4.6,"mp5_Growth_Rate":0.42, "smallimg": "assets/images/god_thumbs/1919.jpg", "physicalprotection": 20, "physicalprotection_Growth_Rate": 3.2, "magicalprotection": 30, "magicalprotection_Growth_Rate": 0.9}},
{"model": "gods", "data": {"name":"Awilix","summary":"","title":"Goddess of the Moon","pantheon":"Mayan","type":"MeleePhysical","class":"Assassin","pros":"High Single Target Damage High Mobility","difficulty":"Hard","release_date":"December 17 2014","favor":5500,"gems":200,"voicelines":"Awilix voicelines","voice_actor":"Bryn Apprill","health":475,"health_Growth_Rate":77,"mana":220,"mana_Growth_Rate":38,"speed":370,"speed_Growth_Rate":0,"range":16,"range_Growth_Rate":0,"attack_Sec":1,"attack_Sec_Growth_Rate":0.0189,"damage":38,"damage_Growth_Rate":2.16,"damage_Growth_Rate_2":"100% of Physical Power","progression":"1/0.75/1.25x damage.","physical":13,"physical_Growth_Rate":3,"magical":30,"magical_Growth_Rate":0.9,"hp5":10,"hp5_Growth_Rate":0.68,"mp5":3.9,"mp5_Growth_Rate":0.27, "smallimg": "assets/images/god_thumbs/2037.jpg", "physicalprotection": 13, "physicalprotection_Growth_Rate": 3, "magicalprotection": 30, "magicalprotection_Growth_Rate": 0.9}},
{"model": "gods", "data": {"name":"Bacchus","summary":"","title":"God of Wine","pantheon":"Roman","type":"MeleeMagical","class":"Guardian","pros":"High Crowd Control High Defense","difficulty":"Average","release_date":"November 19 2012","favor":5500,"gems":200,"voicelines":"Bacchus voicelines","voice_actor":"Chris Rager","health":495,"health_Growth_Rate":86,"mana":200,"mana_Growth_Rate":40,"speed":365,"speed_Growth_Rate":0,"range":12,"range_Growth_Rate":0,"attack_Sec":0.88,"attack_Sec_Growth_Rate":0.01,"damage":37,"damage_Growth_Rate":1.5,"damage_Growth_Rate_2":"20% of Magical Power","progression":"None","physical":19,"physical_Growth_Rate":3,"magical":30,"magical_Growth_Rate":0.9,"hp5":8,"hp5_Growth_Rate":0.8,"mp5":4.8,"mp5_Growth_Rate":0.4, "smallimg": "assets/images/god_thumbs/1809.jpg", "physicalprotection": 19, "physicalprotection_Growth_Rate": 3, "magicalprotection": 30, "magicalprotection_Growth_Rate": 0.9}},
{"model": "gods", "data": {"name":"Bakasura","summary":"","title":"The Great Devourer","pantheon":"Hindu","type":"MeleePhysical","class":"Assassin","pros":"High Single Target Damage","difficulty":"Easy","release_date":"July 20 2012","favor":5500,"gems":200,"voicelines":"Bakasura voicelines","voice_actor":"Brad M. Jackson","health":455,"health_Growth_Rate":78,"mana":200,"mana_Growth_Rate":39,"speed":370,"speed_Growth_Rate":0,"range":12,"range_Growth_Rate":0,"attack_Sec":1,"attack_Sec_Growth_Rate":0.016,"damage":38,"damage_Growth_Rate":2.2,"damage_Growth_Rate_2":"100% of Physical Power","progression":"None","physical":13,"physical_Growth_Rate":2.8,"magical":30,"magical_Growth_Rate":0.9,"hp5":9,"hp5_Growth_Rate":0.68,"mp5":4.8,"mp5_Growth_Rate":0.46, "smallimg": "assets/images/god_thumbs/1755.jpg", "physicalprotection": 13, "physicalprotection_Growth_Rate": 2.8, "magicalprotection": 30, "magicalprotection_Growth_Rate": 0.9}},
{"model": "gods", "data": {"name":"Bastet","summary":"","title":"Goddess of Cats","pantheon":"Egyptian","type":"MeleePhysical","class":"Assassin","pros":"High Single Target Damage","difficulty":"Easy","release_date":"May 31 2012","favor":5500,"gems":200,"voicelines":"Bastet voicelines","voice_actor":"Leah Clark","health":415,"health_Growth_Rate":80,"mana":215,"mana_Growth_Rate":39,"speed":375,"speed_Growth_Rate":0,"range":12,"range_Growth_Rate":0,"attack_Sec":1,"attack_Sec_Growth_Rate":0.0198,"damage":38,"damage_Growth_Rate":2.13,"damage_Growth_Rate_2":"100% of Physical Power","progression":"1/.7/1.3x damage","physical":12,"physical_Growth_Rate":2.9,"magical":30,"magical_Growth_Rate":0.9,"hp5":9,"hp5_Growth_Rate":0.72,"mp5":4.4,"mp5_Growth_Rate":0.18, "smallimg": "assets/images/god_thumbs/1678.jpg", "physicalprotection": 12, "physicalprotection_Growth_Rate": 2.9, "magicalprotection": 30, "magicalprotection_Growth_Rate": 0.9}},
{"model": "gods", "data": {"name":"Bellona","summary":"","title":"Goddess of War","pantheon":"Roman","type":"MeleePhysical","class":"Warrior","pros":"High Defense","difficulty":"Average","release_date":"February 25 2015","favor":5500,"gems":200,"voicelines":"Bellona voicelines","voice_actor":"Laura Post","health":480,"health_Growth_Rate":85,"mana":220,"mana_Growth_Rate":35,"speed":375,"speed_Growth_Rate":0,"range":12,"range_Growth_Rate":0,"attack_Sec":1,"attack_Sec_Growth_Rate":0.012,"damage":39,"damage_Growth_Rate":2,"damage_Growth_Rate_2":"100% of Physical Power","progression":"Special (1/.5/1.5x damage and swing time)","physical":18,"physical_Growth_Rate":3,"magical":30,"magical_Growth_Rate":0.9,"hp5":8,"hp5_Growth_Rate":0.8,"mp5":4.8,"mp5_Growth_Rate":0.4, "smallimg": "assets/images/god_thumbs/2047.jpg", "physicalprotection": 18, "physicalprotection_Growth_Rate": 3, "magicalprotection": 30, "magicalprotection_Growth_Rate": 0.9}},
{"model": "gods", "data": {"name":"Cabrakan","summary":"","title":"Destroyer of Mountains","pantheon":"Mayan","type":"MeleeMagical","class":"Guardian","pros":"High Crowd Control High Defense","difficulty":"Average","release_date":"August 19 2014","favor":5500,"gems":200,"voicelines":"Cabrakan voicelines","voice_actor":"Tyson Rinehart","health":490,"health_Growth_Rate":90,"mana":200,"mana_Growth_Rate":34,"speed":365,"speed_Growth_Rate":0,"range":12,"range_Growth_Rate":0,"attack_Sec":0.9,"attack_Sec_Growth_Rate":0.012,"damage":38,"damage_Growth_Rate":1.5,"damage_Growth_Rate_2":"20%% of Magical Power","progression":"None","physical":23,"physical_Growth_Rate":3.3,"magical":30,"magical_Growth_Rate":0.9,"hp5":8,"hp5_Growth_Rate":0.75,"mp5":4.6,"mp5_Growth_Rate":0.42, "smallimg": "assets/images/god_thumbs/2008.jpg", "physicalprotection": 23, "physicalprotection_Growth_Rate": 3.3, "magicalprotection": 30, "magicalprotection_Growth_Rate": 0.9}},
{"model": "gods", "data": {"name":"Chaac","summary":"","title":"God of Rain","pantheon":"Mayan","type":"MeleePhysical","class":"Warrior","pros":"High Sustain","difficulty":"Average","release_date":"December 18 2013","favor":5500,"gems":200,"voicelines":"Chaac voicelines","voice_actor":"Patrick Seitz","health":480,"health_Growth_Rate":85,"mana":205,"mana_Growth_Rate":35,"speed":375,"speed_Growth_Rate":0,"range":12,"range_Growth_Rate":0,"attack_Sec":1,"attack_Sec_Growth_Rate":0.01,"damage":39,"damage_Growth_Rate":2.1,"damage_Growth_Rate_2":"100% of Physical Power","progression":"1/.5/1.5x damage","physical":18,"physical_Growth_Rate":3,"magical":30,"magical_Growth_Rate":0.9,"hp5":7,"hp5_Growth_Rate":0.8,"mp5":4.7,"mp5_Growth_Rate":0.39, "smallimg": "assets/images/god_thumbs/1966.jpg", "physicalprotection": 18, "physicalprotection_Growth_Rate": 3, "magicalprotection": 30, "magicalprotection_Growth_Rate": 0.9}},
{"model": "gods", "data": {"name":"Chang'e","summary":"","title":"Faerie of the Moon","pantheon":"Chinese","type":"RangedMagical","class":"Mage","pros":"High Sustain High Mobility","difficulty":"Average","release_date":"July 24 2013","favor":5500,"gems":200,"voicelines":"Chang'e voicelines","voice_actor":"Chang'e: Trina NishimuraJade Rabbit: Ric Spiegel","health":375,"health_Growth_Rate":70,"mana":290,"mana_Growth_Rate":43,"speed":355,"speed_Growth_Rate":0,"range":55,"range_Growth_Rate":0,"attack_Sec":1,"attack_Sec_Growth_Rate":0.0095,"damage":32,"damage_Growth_Rate":1.45,"damage_Growth_Rate_2":"20% of Magical Power","progression":"None","physical":11,"physical_Growth_Rate":2.7,"magical":30,"magical_Growth_Rate":0,"hp5":6,"hp5_Growth_Rate":0.45,"mp5":5.5,"mp5_Growth_Rate":0.44, "smallimg": "assets/images/god_thumbs/1921.jpg", "physicalprotection": 11, "physicalprotection_Growth_Rate": 2.7, "magicalprotection": 30, "magicalprotection_Growth_Rate": 0}},
{"model": "gods", "data": {"name":"Chiron","summary":"","title":"The Great Teacher","pantheon":"Greek","type":"RangedPhysical","class":"Hunter","pros":"High Sustain High Movement Speed","difficulty":"Easy","release_date":"November 17 2015","favor":5500,"gems":200,"voicelines":"Chiron voicelines","voice_actor":"","health":460,"health_Growth_Rate":75,"mana":225,"mana_Growth_Rate":40,"speed":380,"speed_Growth_Rate":0,"range":55,"range_Growth_Rate":0,"attack_Sec":1,"attack_Sec_Growth_Rate":0.011,"damage":35,"damage_Growth_Rate":2.35,"damage_Growth_Rate_2":"100% of Physical Power","progression":"None","physical":12,"physical_Growth_Rate":2.8,"magical":30,"magical_Growth_Rate":0.9,"hp5":6,"hp5_Growth_Rate":0.65,"mp5":4.4,"mp5_Growth_Rate":0.38, "smallimg": "assets/images/god_thumbs/Chiron.png", "physicalprotection": 12, "physicalprotection_Growth_Rate": 2.8, "magicalprotection": 30, "magicalprotection_Growth_Rate": 0.9}},
{"model": "gods", "data": {"name":"Chronos","summary":"","title":"Keeper of Time","pantheon":"Greek","type":"RangedMagical","class":"Mage","pros":"Medium Crowd Control High Mobility","difficulty":"Hard","release_date":"July 10 2013","favor":5500,"gems":200,"voicelines":"Chronos voicelines","voice_actor":"Stan Robak","health":370,"health_Growth_Rate":70,"mana":240,"mana_Growth_Rate":42,"speed":355,"speed_Growth_Rate":0,"range":55,"range_Growth_Rate":0,"attack_Sec":1,"attack_Sec_Growth_Rate":0.008,"damage":35,"damage_Growth_Rate":1.5,"damage_Growth_Rate_2":"20% of Magical Power","progression":"None","physical":11,"physical_Growth_Rate":2.9,"magical":30,"magical_Growth_Rate":0,"hp5":7,"hp5_Growth_Rate":0.48,"mp5":4.4,"mp5_Growth_Rate":0.44, "smallimg": "assets/images/god_thumbs/1920.jpg", "physicalprotection": 11, "physicalprotection_Growth_Rate": 2.9, "magicalprotection": 30, "magicalprotection_Growth_Rate": 0}},
{"model": "gods", "data": {"name":"Cupid","summary":"","title":"God of Love","pantheon":"Roman","type":"RangedPhysical","class":"Hunter","pros":"High Single Target Damage High Sustain","difficulty":"Easy","release_date":"August 17 2012","favor":1500,"gems":200,"voicelines":"Cupid voicelines","voice_actor":"Brina Palencia","health":445,"health_Growth_Rate":72,"mana":230,"mana_Growth_Rate":39,"speed":365,"speed_Growth_Rate":0,"range":55,"range_Growth_Rate":0,"attack_Sec":0.95,"attack_Sec_Growth_Rate":0.018,"damage":35,"damage_Growth_Rate":2.3,"damage_Growth_Rate_2":"100% of Physical Power","progression":"None","physical":11,"physical_Growth_Rate":3,"magical":30,"magical_Growth_Rate":0.9,"hp5":8,"hp5_Growth_Rate":0.67,"mp5":4.6,"mp5_Growth_Rate":0.35, "smallimg": "assets/images/god_thumbs/1778.jpg", "physicalprotection": 11, "physicalprotection_Growth_Rate": 3, "magicalprotection": 30, "magicalprotection_Growth_Rate": 0.9}},
{"model": "gods", "data": {"name":"Fenrir","summary":"","title":"The Unbound","pantheon":"Norse","type":"MeleePhysical","class":"Assassin","pros":"High Single Target Damage High Mobility","difficulty":"Average","release_date":"May 1 2013","favor":5500,"gems":200,"voicelines":"Fenrir voicelines","voice_actor":"Christopher Sabat","health":455,"health_Growth_Rate":78,"mana":200,"mana_Growth_Rate":35,"speed":370,"speed_Growth_Rate":0,"range":12,"range_Growth_Rate":0,"attack_Sec":1,"attack_Sec_Growth_Rate":0.017,"damage":38,"damage_Growth_Rate":2.3,"damage_Growth_Rate_2":"100% of Physical Power","progression":"None","physical":14,"physical_Growth_Rate":3,"magical":30,"magical_Growth_Rate":0.9,"hp5":8,"hp5_Growth_Rate":0.73,"mp5":3.7,"mp5_Growth_Rate":0.26, "smallimg": "assets/images/god_thumbs/1843.jpg", "physicalprotection": 14, "physicalprotection_Growth_Rate": 3, "magicalprotection": 30, "magicalprotection_Growth_Rate": 0.9}},
{"model": "gods", "data": {"name":"Freya","summary":"","title":"Queen of the Valkyries","pantheon":"Norse","type":"MeleeMagical","class":"Mage","pros":"Medium Crowd Control High Area Damage","difficulty":"Average","release_date":"October 18 2012","favor":5500,"gems":200,"voicelines":"Freya voicelines","voice_actor":"Jamie Marchi","health":405,"health_Growth_Rate":80,"mana":220,"mana_Growth_Rate":37,"speed":375,"speed_Growth_Rate":0,"range":12,"range_Growth_Rate":0,"attack_Sec":0.95,"attack_Sec_Growth_Rate":0.0195,"damage":35,"damage_Growth_Rate":1.5,"damage_Growth_Rate_2":"20% of Magical Power","progression":"None","physical":14,"physical_Growth_Rate":2.8,"magical":30,"magical_Growth_Rate":0.9,"hp5":7,"hp5_Growth_Rate":0.52,"mp5":4.5,"mp5_Growth_Rate":0.39, "smallimg": "assets/images/god_thumbs/1784.jpg", "physicalprotection": 14, "physicalprotection_Growth_Rate": 2.8, "magicalprotection": 30, "magicalprotection_Growth_Rate": 0.9}},
{"model": "gods", "data": {"name":"Geb","summary":"","title":"God of Earth","pantheon":"Egyptian","type":"MeleeMagical","class":"Guardian","pros":"High Crowd Control High Defense","difficulty":"Average","release_date":"January 16 2014","favor":5500,"gems":200,"voicelines":"Geb voicelines","voice_actor":"Christopher Sabat","health":510,"health_Growth_Rate":90,"mana":190,"mana_Growth_Rate":34,"speed":360,"speed_Growth_Rate":0,"range":12,"range_Growth_Rate":0,"attack_Sec":1,"attack_Sec_Growth_Rate":0.012,"damage":38,"damage_Growth_Rate":1.5,"damage_Growth_Rate_2":"20% of Magical Power","progression":"1/1/1/1x damage","physical":19,"physical_Growth_Rate":3,"magical":30,"magical_Growth_Rate":0.9,"hp5":8,"hp5_Growth_Rate":0.8,"mp5":4.6,"mp5_Growth_Rate":0.4, "smallimg": "assets/images/god_thumbs/1978.jpg", "physicalprotection": 19, "physicalprotection_Growth_Rate": 3, "magicalprotection": 30, "magicalprotection_Growth_Rate": 0.9}},
{"model": "gods", "data": {"name":"Guan Yu","summary":"","title":"Saint of War","pantheon":"Chinese","type":"MeleePhysical","class":"Warrior","pros":"High Sustain High Mobility","difficulty":"Average","release_date":"June 29 2012","favor":"(Free) 0","gems":"(Free) 0","voicelines":"Guan Yu voicelines","voice_actor":"Mark Stoddard","health":470,"health_Growth_Rate":84,"mana":220,"mana_Growth_Rate":32,"speed":375,"speed_Growth_Rate":0,"range":12,"range_Growth_Rate":0,"attack_Sec":1,"attack_Sec_Growth_Rate":0.009,"damage":37,"damage_Growth_Rate":2,"damage_Growth_Rate_2":"100% of Physical Power","progression":"1/1/1.3/1.75x damage and swing time","physical":16,"physical_Growth_Rate":3,"magical":30,"magical_Growth_Rate":0.9,"hp5":6,"hp5_Growth_Rate":0.7,"mp5":4.8,"mp5_Growth_Rate":0.45, "smallimg": "assets/images/god_thumbs/1763.jpg", "physicalprotection": 16, "physicalprotection_Growth_Rate": 3, "magicalprotection": 30, "magicalprotection_Growth_Rate": 0.9}},
{"model": "gods", "data": {"name":"Hades","summary":"","title":"King of the Underworld","pantheon":"Greek","type":"RangedMagical","class":"Mage","pros":"High Defense High Sustain","difficulty":"Easy","release_date":"May 31 2012","favor":2000,"gems":200,"voicelines":"Hades voicelines","voice_actor":"Patrick Seitz","health":490,"health_Growth_Rate":80,"mana":265,"mana_Growth_Rate":53,"speed":355,"speed_Growth_Rate":0,"range":55,"range_Growth_Rate":0,"attack_Sec":0.87,"attack_Sec_Growth_Rate":0.0105,"damage":32,"damage_Growth_Rate":1.5,"damage_Growth_Rate_2":"20% of Magical Power","progression":"None","physical":18,"physical_Growth_Rate":3.2,"magical":30,"magical_Growth_Rate":0.9,"hp5":5,"hp5_Growth_Rate":0.54,"mp5":5,"mp5_Growth_Rate":0.36, "smallimg": "assets/images/god_thumbs/1676.jpg", "physicalprotection": 18, "physicalprotection_Growth_Rate": 3.2, "magicalprotection": 30, "magicalprotection_Growth_Rate": 0.9}},
{"model": "gods", "data": {"name":"He Bo","summary":"","title":"God of the Yellow River","pantheon":"Chinese","type":"RangedMagical","class":"Mage","pros":"Medium Crowd Control High Area Damage","difficulty":"Easy","release_date":"May 31 2012","favor":5500,"gems":200,"voicelines":"He Bo voicelines","voice_actor":"Christopher Sabat","health":365,"health_Growth_Rate":68,"mana":298,"mana_Growth_Rate":56,"speed":350,"speed_Growth_Rate":0,"range":55,"range_Growth_Rate":0,"attack_Sec":0.86,"attack_Sec_Growth_Rate":0.009,"damage":34,"damage_Growth_Rate":1.45,"damage_Growth_Rate_2":"20% of Magical Power","progression":"None","physical":9,"physical_Growth_Rate":2.6,"magical":30,"magical_Growth_Rate":0,"hp5":6,"hp5_Growth_Rate":0.45,"mp5":4.9,"mp5_Growth_Rate":0.4, "smallimg": "assets/images/god_thumbs/1674.jpg", "physicalprotection": 9, "physicalprotection_Growth_Rate": 2.6, "magicalprotection": 30, "magicalprotection_Growth_Rate": 0}},
{"model": "gods", "data": {"name":"Hel","summary":"","title":"Goddess of the Underworld","pantheon":"Norse","type":"RangedMagical","class":"Mage","pros":"High Sustain High Area Damage","difficulty":"Hard","release_date":"May 31 2012","favor":5500,"gems":200,"voicelines":"Hel voicelines","voice_actor":"Monica Rial","health":345,"health_Growth_Rate":67,"mana":300,"mana_Growth_Rate":57,"speed":350,"speed_Growth_Rate":0,"range":55,"range_Growth_Rate":0,"attack_Sec":0.86,"attack_Sec_Growth_Rate":0.009,"damage":33,"damage_Growth_Rate":1.5,"damage_Growth_Rate_2":"20% of Magical Power","progression":"None","physical":9,"physical_Growth_Rate":2.6,"magical":30,"magical_Growth_Rate":0,"hp5":5,"hp5_Growth_Rate":0.43,"mp5":5,"mp5_Growth_Rate":0.45, "smallimg": "assets/images/god_thumbs/1718.jpg", "physicalprotection": 9, "physicalprotection_Growth_Rate": 2.6, "magicalprotection": 30, "magicalprotection_Growth_Rate": 0}},
{"model": "gods", "data": {"name":"Hercules","summary":"","title":"Champion of Rome","pantheon":"Roman","type":"MeleePhysical","class":"Warrior","pros":"High Single Target Damage High Sustain","difficulty":"Easy","release_date":"January 9 2013","favor":5500,"gems":200,"voicelines":"Hercules voicelines","voice_actor":"J. Michael Tatum","health":480,"health_Growth_Rate":86,"mana":205,"mana_Growth_Rate":32,"speed":375,"speed_Growth_Rate":0,"range":12,"range_Growth_Rate":0,"attack_Sec":1,"attack_Sec_Growth_Rate":0.008,"damage":39,"damage_Growth_Rate":2,"damage_Growth_Rate_2":"100% of Physical Power","progression":"1/1/1.5x damage and swing time","physical":18,"physical_Growth_Rate":3,"magical":30,"magical_Growth_Rate":0.9,"hp5":7,"hp5_Growth_Rate":0.63,"mp5":4.3,"mp5_Growth_Rate":0.4, "smallimg": "assets/images/god_thumbs/1848.jpg", "physicalprotection": 18, "physicalprotection_Growth_Rate": 3, "magicalprotection": 30, "magicalprotection_Growth_Rate": 0.9}},
{"model": "gods", "data": {"name":"Hou Yi","summary":"","title":"Defender of the Earth","pantheon":"Chinese","type":"RangedPhysical","class":"Hunter","pros":"High Single Target Damage High Area Damage","difficulty":"Hard","release_date":"January 14 2015","favor":5500,"gems":200,"voicelines":"Hou Yi voicelines","voice_actor":"Austin Tindle","health":480,"health_Growth_Rate":78,"mana":240,"mana_Growth_Rate":38,"speed":370,"speed_Growth_Rate":0,"range":55,"range_Growth_Rate":0,"attack_Sec":0.9,"attack_Sec_Growth_Rate":0.012,"damage":38,"damage_Growth_Rate":2.8,"damage_Growth_Rate_2":"100% of Physical Power","progression":"None","physical":13,"physical_Growth_Rate":2.8,"magical":30,"magical_Growth_Rate":0.9,"hp5":8,"hp5_Growth_Rate":0.68,"mp5":5,"mp5_Growth_Rate":0.35, "smallimg": "assets/images/god_thumbs/2040.jpg", "physicalprotection": 13, "physicalprotection_Growth_Rate": 2.8, "magicalprotection": 30, "magicalprotection_Growth_Rate": 0.9}},
{"model": "gods", "data": {"name":"Hun Batz","summary":"","title":"The Howler Monkey God","pantheon":"Mayan","type":"MeleePhysical","class":"Assassin","pros":"High Single Target Damage","difficulty":"Easy","release_date":"May 31 2012","favor":5500,"gems":200,"voicelines":"Hun Batz voicelines","voice_actor":"Brad M. Jackson","health":460,"health_Growth_Rate":75,"mana":220,"mana_Growth_Rate":38,"speed":370,"speed_Growth_Rate":0,"range":12,"range_Growth_Rate":0,"attack_Sec":1,"attack_Sec_Growth_Rate":0.0189,"damage":38,"damage_Growth_Rate":2.13,"damage_Growth_Rate_2":"100% of Physical Power","progression":"1/.75/1.25x damage","physical":13,"physical_Growth_Rate":3,"magical":30,"magical_Growth_Rate":0.9,"hp5":10,"hp5_Growth_Rate":0.68,"mp5":3.9,"mp5_Growth_Rate":0.27, "smallimg": "assets/images/god_thumbs/1673.jpg", "physicalprotection": 13, "physicalprotection_Growth_Rate": 3, "magicalprotection": 30, "magicalprotection_Growth_Rate": 0.9}},
{"model": "gods", "data": {"name":"Isis","summary":"","title":"Goddess of Magic","pantheon":"Egyptian","type":"RangedMagical","class":"Mage","pros":"High Crowd Control High Area Damage","difficulty":"Average","release_date":"May 15 2013","favor":5500,"gems":200,"voicelines":"Isis voicelines","voice_actor":"Caitlin Glass","health":365,"health_Growth_Rate":68,"mana":280,"mana_Growth_Rate":51,"speed":355,"speed_Growth_Rate":0,"range":55,"range_Growth_Rate":0,"attack_Sec":1,"attack_Sec_Growth_Rate":0.00,"damage":35,"damage_Growth_Rate":1.5,"damage_Growth_Rate_2":"20% of Magical Power","progression":"1/1/1.5x damage and swing time hitting in a 6ft AoE on the final blow","physical":9,"physical_Growth_Rate":2.7,"magical":30,"magical_Growth_Rate":0,"hp5":6,"hp5_Growth_Rate":0.45,"mp5":4.8,"mp5_Growth_Rate":0.43, "smallimg": "assets/images/god_thumbs/1918.jpg", "physicalprotection": 9, "physicalprotection_Growth_Rate": 2.7, "magicalprotection": 30, "magicalprotection_Growth_Rate": 0}},
{"model": "gods", "data": {"name":"Janus","summary":"","title":"God of Portals and Transitions","pantheon":"Roman","type":"RangedMagical","class":"Mage","pros":"High Mobility High Area Damage","difficulty":"Average","release_date":"May 28 2014","favor":5500,"gems":200,"voicelines":"Janus voicelines","voice_actor":"Sean Hennigan","health":400,"health_Growth_Rate":70,"mana":350,"mana_Growth_Rate":58,"speed":360,"speed_Growth_Rate":0,"range":55,"range_Growth_Rate":0,"attack_Sec":1,"attack_Sec_Growth_Rate":0.008,"damage":34,"damage_Growth_Rate":1.45,"damage_Growth_Rate_2":"20% of Magical Power","progression":"None","physical":8,"physical_Growth_Rate":2.6,"magical":30,"magical_Growth_Rate":0,"hp5":6,"hp5_Growth_Rate":0.45,"mp5":5,"mp5_Growth_Rate":0.45, "smallimg": "assets/images/god_thumbs/1999.jpg", "physicalprotection": 8, "physicalprotection_Growth_Rate": 2.6, "magicalprotection": 30, "magicalprotection_Growth_Rate": 0}},
{"model": "gods", "data": {"name":"Jing Wei","summary":"","title":"The Oathkeeper","pantheon":"Chinese","type":"RangedPhysical","class":"Hunter","pros":"High Mobility","difficulty":"Easy","release_date":"","favor":10000,"gems":200,"voicelines":"Jing Wei voicelines","voice_actor":"","health":445,"health_Growth_Rate":78,"mana":205,"mana_Growth_Rate":36,"speed":370,"speed_Growth_Rate":0,"range":55,"range_Growth_Rate":0,"attack_Sec":1,"attack_Sec_Growth_Rate":0.014,"damage":38,"damage_Growth_Rate":2.5,"damage_Growth_Rate_2":"100% of Physical Power","progression":"None","physical":11,"physical_Growth_Rate":2.9,"magical":30,"magical_Growth_Rate":0.9,"hp5":7,"hp5_Growth_Rate":0.68,"mp5":4.4,"mp5_Growth_Rate":0.3, "smallimg": "", "physicalprotection": 11, "physicalprotection_Growth_Rate": 2.9, "magicalprotection": 30, "magicalprotection_Growth_Rate": 0.9}},
{"model": "gods", "data": {"name":"Kali","summary":"","title":"Goddess of Destruction","pantheon":"Hindu","type":"MeleePhysical","class":"Assassin","pros":"High Single Target Damage High Sustain","difficulty":"Average","release_date":"May 31 2012","favor":5500,"gems":200,"voicelines":"Kali voicelines","voice_actor":"Anastasia Munoz","health":470,"health_Growth_Rate":74,"mana":205,"mana_Growth_Rate":34,"speed":375,"speed_Growth_Rate":0,"range":12,"range_Growth_Rate":0,"attack_Sec":1,"attack_Sec_Growth_Rate":0.0216,"damage":37,"damage_Growth_Rate":2.32,"damage_Growth_Rate_2":"100% of Physical Power","progression":"1/.5/.5x damage and swing time","physical":15,"physical_Growth_Rate":2.9,"magical":30,"magical_Growth_Rate":0.9,"hp5":9,"hp5_Growth_Rate":0.68,"mp5":4.3,"mp5_Growth_Rate":0.21, "smallimg": "assets/images/god_thumbs/1649.jpg", "physicalprotection": 15, "physicalprotection_Growth_Rate": 2.9, "magicalprotection": 30, "magicalprotection_Growth_Rate": 0.9}},
{"model": "gods", "data": {"name":"Khepri","summary":"","title":"The Dawn Bringer","pantheon":"Egyptian","type":"MeleeMagical","class":"Guardian","pros":"High Crowd Control High Defense","difficulty":"Average","release_date":"August 4 2015","favor":5500,"gems":200,"voicelines":"Khepri voicelines","voice_actor":"","health":460,"health_Growth_Rate":90,"mana":190,"mana_Growth_Rate":34,"speed":360,"speed_Growth_Rate":0,"range":12,"range_Growth_Rate":0,"attack_Sec":1,"attack_Sec_Growth_Rate":0.012,"damage":38,"damage_Growth_Rate":1.5,"damage_Growth_Rate_2":"20% of Magical Power","progression":"1/.5/1.5x damage and swing time","physical":19,"physical_Growth_Rate":3,"magical":30,"magical_Growth_Rate":0.9,"hp5":8,"hp5_Growth_Rate":0.8,"mp5":5,"mp5_Growth_Rate":0.4, "smallimg": "assets/images/god_thumbs/khepri.jpg", "physicalprotection": 19, "physicalprotection_Growth_Rate": 3, "magicalprotection": 30, "magicalprotection_Growth_Rate": 0.9}},
{"model": "gods", "data": {"name":"Kukulkan","summary":"","title":"Serpent of the Nine Winds","pantheon":"Mayan","type":"RangedMagical","class":"Mage","pros":"Pusher High Area Damage","difficulty":"Easy","release_date":"May 31 2012","favor":2500,"gems":200,"voicelines":"Kukulkan voicelines","voice_actor":"Clifford Chapin","health":365,"health_Growth_Rate":68,"mana":265,"mana_Growth_Rate":45,"speed":350,"speed_Growth_Rate":0,"range":55,"range_Growth_Rate":0,"attack_Sec":0.87,"attack_Sec_Growth_Rate":0.0091,"damage":34,"damage_Growth_Rate":1.45,"damage_Growth_Rate_2":"20% of Magical Power","progression":"None","physical":13,"physical_Growth_Rate":3,"magical":30,"magical_Growth_Rate":0,"hp5":7,"hp5_Growth_Rate":0.46,"mp5":5,"mp5_Growth_Rate":0.45, "smallimg": "assets/images/god_thumbs/1677.jpg", "physicalprotection": 13, "physicalprotection_Growth_Rate": 3, "magicalprotection": 30, "magicalprotection_Growth_Rate": 0}},
{"model": "gods", "data": {"name":"Kumbhakarna","summary":"","title":"The Sleeping Giant","pantheon":"Hindu","type":"MeleeMagical","class":"Guardian","pros":"High Crowd Control High Defense","difficulty":"Easy","release_date":"April 16 2014","favor":5500,"gems":200,"voicelines":"Kumbhakarna voicelines","voice_actor":"Jeremy Inman","health":490,"health_Growth_Rate":100,"mana":200,"mana_Growth_Rate":34,"speed":365,"speed_Growth_Rate":0,"range":12,"range_Growth_Rate":0,"attack_Sec":1,"attack_Sec_Growth_Rate":0.012,"damage":38,"damage_Growth_Rate":1.5,"damage_Growth_Rate_2":"20% of Magical Power","progression":"1/.75/1.25 damage","physical":18,"physical_Growth_Rate":3.2,"magical":30,"magical_Growth_Rate":0.9,"hp5":8,"hp5_Growth_Rate":0.75,"mp5":4.6,"mp5_Growth_Rate":0.42, "smallimg": "assets/images/god_thumbs/19931.jpg", "physicalprotection": 18, "physicalprotection_Growth_Rate": 3.2, "magicalprotection": 30, "magicalprotection_Growth_Rate": 0.9}},
{"model": "gods", "data": {"name":"Loki","summary":"","title":"The Trickster God","pantheon":"Norse","type":"MeleePhysical","class":"Assassin","pros":"High Single Target Damage","difficulty":"Easy","release_date":"November 2 2012","favor":5500,"gems":200,"voicelines":"Loki voicelines","voice_actor":"Alex Ross","health":395,"health_Growth_Rate":75,"mana":210,"mana_Growth_Rate":35,"speed":375,"speed_Growth_Rate":0,"range":12,"range_Growth_Rate":0,"attack_Sec":1,"attack_Sec_Growth_Rate":0.019,"damage":38,"damage_Growth_Rate":2.4,"damage_Growth_Rate_2":"100% of Physical Power","progression":"1/.5/.5/.5/1.5x damage and swing time","physical":11,"physical_Growth_Rate":2.9,"magical":30,"magical_Growth_Rate":0.9,"hp5":8,"hp5_Growth_Rate":0.7,"mp5":4.2,"mp5_Growth_Rate":0.35, "smallimg": "assets/images/god_thumbs/lokistandard1.jpg", "physicalprotection": 11, "physicalprotection_Growth_Rate": 2.9, "magicalprotection": 30, "magicalprotection_Growth_Rate": 0.9}},
{"model": "gods", "data": {"name":"Medusa","summary":"","title":"The Gorgon","pantheon":"Greek","type":"RangedPhysical","class":"Hunter","pros":"High Single Target Damage","difficulty":"Easy","release_date":"April 1 2015","favor":5500,"gems":200,"voicelines":"Medusa voicelines","voice_actor":"Rachel Robinson","health":470,"health_Growth_Rate":77,"mana":220,"mana_Growth_Rate":34,"speed":365,"speed_Growth_Rate":0,"range":55,"range_Growth_Rate":0,"attack_Sec":0.95,"attack_Sec_Growth_Rate":0.014,"damage":38,"damage_Growth_Rate":2.6,"damage_Growth_Rate_2":"100% of Physical Power","progression":"None","physical":12,"physical_Growth_Rate":3,"magical":30,"magical_Growth_Rate":0.9,"hp5":8,"hp5_Growth_Rate":0.68,"mp5":4.4,"mp5_Growth_Rate":0.25, "smallimg": "assets/images/god_thumbs/2051.jpg", "physicalprotection": 12, "physicalprotection_Growth_Rate": 3, "magicalprotection": 30, "magicalprotection_Growth_Rate": 0.9}},
{"model": "gods", "data": {"name":"Mercury","summary":"","title":"Messenger of the Gods","pantheon":"Roman","type":"MeleePhysical","class":"Assassin","pros":"High Single Target Damage High Mobility","difficulty":"Average","release_date":"October 2 2013","favor":5500,"gems":200,"voicelines":"Mercury voicelines","voice_actor":"Joel McDonald","health":400,"health_Growth_Rate":75,"mana":200,"mana_Growth_Rate":40,"speed":375,"speed_Growth_Rate":0,"range":12,"range_Growth_Rate":0,"attack_Sec":1,"attack_Sec_Growth_Rate":0.024,"damage":38,"damage_Growth_Rate":2.13,"damage_Growth_Rate_2":"100% of Physical Power","progression":"1/.75/1.25x damage","physical":12,"physical_Growth_Rate":2.9,"magical":30,"magical_Growth_Rate":0.9,"hp5":10,"hp5_Growth_Rate":0.7,"mp5":4.4,"mp5_Growth_Rate":0.35, "smallimg": "assets/images/god_thumbs/1941.jpg", "physicalprotection": 12, "physicalprotection_Growth_Rate": 2.9, "magicalprotection": 30, "magicalprotection_Growth_Rate": 0.9}},
{"model": "gods", "data": {"name":"Ne Zha","summary":"","title":"The Third Lotus Prince","pantheon":"Chinese","type":"MeleePhysical","class":"Assassin","pros":"High Single Target Damage Medium Crowd Control","difficulty":"Average","release_date":"April 17 2013","favor":5500,"gems":200,"voicelines":"Ne Zha voicelines","voice_actor":"Colleen Clinkenbeard","health":400,"health_Growth_Rate":75,"mana":200,"mana_Growth_Rate":35,"speed":375,"speed_Growth_Rate":0,"range":12,"range_Growth_Rate":0,"attack_Sec":1,"attack_Sec_Growth_Rate":0.021,"damage":39,"damage_Growth_Rate":2.2,"damage_Growth_Rate_2":"100% of Physical Power","progression":"1/1/1.5/2x damage and swing time hitting in an AoE on the final blow","physical":12,"physical_Growth_Rate":2.9,"magical":30,"magical_Growth_Rate":0.9,"hp5":10,"hp5_Growth_Rate":0.71,"mp5":3.9,"mp5_Growth_Rate":0.27, "smallimg": "assets/images/god_thumbs/1915.jpg", "physicalprotection": 12, "physicalprotection_Growth_Rate": 2.9, "magicalprotection": 30, "magicalprotection_Growth_Rate": 0.9}},
{"model": "gods", "data": {"name":"Neith","summary":"","title":"Weaver of Fate","pantheon":"Egyptian","type":"RangedPhysical","class":"Hunter","pros":"High Crowd Control High Sustain","difficulty":"Easy","release_date":"February 13 2013","favor":"(Free) 0","gems":"(Free) 0","voicelines":"Neith voicelines","voice_actor":"Lindsay Seidel","health":435,"health_Growth_Rate":75,"mana":230,"mana_Growth_Rate":39,"speed":365,"speed_Growth_Rate":0,"range":55,"range_Growth_Rate":0,"attack_Sec":0.95,"attack_Sec_Growth_Rate":0.016,"damage":35,"damage_Growth_Rate":2.3,"damage_Growth_Rate_2":"100% of Physical Power","progression":"None","physical":12,"physical_Growth_Rate":3,"magical":30,"magical_Growth_Rate":0.9,"hp5":6,"hp5_Growth_Rate":0.54,"mp5":4.4,"mp5_Growth_Rate":0.35, "smallimg": "assets/images/god_thumbs/1872.jpg", "physicalprotection": 12, "physicalprotection_Growth_Rate": 3, "magicalprotection": 30, "magicalprotection_Growth_Rate": 0.9}},
{"model": "gods", "data": {"name":"Nemesis","summary":"","title":"Goddess of Vengeance","pantheon":"Greek","type":"MeleePhysical","class":"Assassin","pros":"High Mobility","difficulty":"Average","release_date":"February 6 2014","favor":5500,"gems":200,"voicelines":"Nemesis voicelines","voice_actor":"Amanda Doskocil","health":470,"health_Growth_Rate":76,"mana":210,"mana_Growth_Rate":38,"speed":375,"speed_Growth_Rate":0,"range":12,"range_Growth_Rate":0,"attack_Sec":1,"attack_Sec_Growth_Rate":0.0216,"damage":39,"damage_Growth_Rate":2.25,"damage_Growth_Rate_2":"100% of Physical Power","progression":"1/1/.75/1.25x damage and swing time","physical":11,"physical_Growth_Rate":3,"magical":30,"magical_Growth_Rate":0.9,"hp5":8,"hp5_Growth_Rate":0.7,"mp5":4.3,"mp5_Growth_Rate":0.4, "smallimg": "assets/images/god_thumbs/19801.jpg", "physicalprotection": 11, "physicalprotection_Growth_Rate": 3, "magicalprotection": 30, "magicalprotection_Growth_Rate": 0.9}},
{"model": "gods", "data": {"name":"Nox","summary":"","title":"Goddess of Night","pantheon":"Roman","type":"RangedMagical","class":"Mage","pros":"High Crowd Control","difficulty":"Average","release_date":"October 29 2014","favor":5500,"gems":200,"voicelines":"Nox voicelines","voice_actor":"Laura Post","health":365,"health_Growth_Rate":75,"mana":250,"mana_Growth_Rate":38,"speed":360,"speed_Growth_Rate":0,"range":55,"range_Growth_Rate":0,"attack_Sec":1,"attack_Sec_Growth_Rate":0.008,"damage":34,"damage_Growth_Rate":1.5,"damage_Growth_Rate_2":"20% of Magical Power","progression":"None","physical":18,"physical_Growth_Rate":2.6,"magical":30,"magical_Growth_Rate":0,"hp5":8,"hp5_Growth_Rate":0.6,"mp5":5,"mp5_Growth_Rate":0.4, "smallimg": "assets/images/god_thumbs/2036.jpg", "physicalprotection": 18, "physicalprotection_Growth_Rate": 2.6, "magicalprotection": 30, "magicalprotection_Growth_Rate": 0}},
{"model": "gods", "data": {"name":"Nu Wa","summary":"","title":"Guardian of Heaven","pantheon":"Chinese","type":"RangedMagical","class":"Mage","pros":"Pusher","difficulty":"Easy","release_date":"December 5 2013","favor":5500,"gems":200,"voicelines":"Nu Wa voicelines","voice_actor":"Stephanie Young","health":400,"health_Growth_Rate":75,"mana":265,"mana_Growth_Rate":43,"speed":355,"speed_Growth_Rate":0,"range":55,"range_Growth_Rate":0,"attack_Sec":1,"attack_Sec_Growth_Rate":0.017,"damage":35,"damage_Growth_Rate":1.5,"damage_Growth_Rate_2":"20% of Magical Power","progression":"None","physical":9,"physical_Growth_Rate":2.7,"magical":30,"magical_Growth_Rate":0,"hp5":7,"hp5_Growth_Rate":0.45,"mp5":4.6,"mp5_Growth_Rate":0.43, "smallimg": "assets/images/god_thumbs/1958.jpg", "physicalprotection": 9, "physicalprotection_Growth_Rate": 2.7, "magicalprotection": 30, "magicalprotection_Growth_Rate": 0}},
{"model": "gods", "data": {"name":"Odin","summary":"","title":"The Allfather","pantheon":"Norse","type":"MeleePhysical","class":"Warrior","pros":"High Crowd Control High Area Damage","difficulty":"Easy","release_date":"May 31 2012","favor":5500,"gems":200,"voicelines":"Odin voicelines","voice_actor":"Bob Carter","health":460,"health_Growth_Rate":80,"mana":200,"mana_Growth_Rate":35,"speed":375,"speed_Growth_Rate":0,"range":12,"range_Growth_Rate":0,"attack_Sec":1,"attack_Sec_Growth_Rate":0.011,"damage":38,"damage_Growth_Rate":2,"damage_Growth_Rate_2":"100% of Physical Power","progression":"1/1/1/1.5x damage and swing time","physical":16,"physical_Growth_Rate":3,"magical":30,"magical_Growth_Rate":0.9,"hp5":9,"hp5_Growth_Rate":0.63,"mp5":4.1,"mp5_Growth_Rate":0.4, "smallimg": "assets/images/god_thumbs/1669.jpg", "physicalprotection": 16, "physicalprotection_Growth_Rate": 3, "magicalprotection": 30, "magicalprotection_Growth_Rate": 0.9}},
{"model": "gods", "data": {"name":"Osiris","summary":"","title":"Broken God of the Afterlife","pantheon":"Egyptian","type":"MeleePhysical","class":"Warrior","pros":"High Defense High Attack Speed","difficulty":"Hard","release_date":"May 6 2014","favor":5500,"gems":200,"voicelines":"Osiris voicelines","voice_actor":"Mike McFarland","health":475,"health_Growth_Rate":85,"mana":230,"mana_Growth_Rate":40,"speed":375,"speed_Growth_Rate":0,"range":12,"range_Growth_Rate":0,"attack_Sec":1,"attack_Sec_Growth_Rate":0.014,"damage":39,"damage_Growth_Rate":2.25,"damage_Growth_Rate_2":"100% of Physical Power","progression":"0.5/1/0.5/1x damage. The last two attacks hit all enemies in the melee area.","physical":17,"physical_Growth_Rate":3,"magical":30,"magical_Growth_Rate":0.9,"hp5":6,"hp5_Growth_Rate":0.8,"mp5":4.7,"mp5_Growth_Rate":0.39, "smallimg": "assets/images/god_thumbs/2000.jpg", "physicalprotection": 17, "physicalprotection_Growth_Rate": 3, "magicalprotection": 30, "magicalprotection_Growth_Rate": 0.9}},
{"model": "gods", "data": {"name":"Poseidon","summary":"","title":"God of the Oceans","pantheon":"Greek","type":"RangedMagical","class":"Mage","pros":"High Area Damage","difficulty":"Easy","release_date":"February 28 2013","favor":5500,"gems":200,"voicelines":"Poseidon voicelines","voice_actor":"Richard Epcar","health":380,"health_Growth_Rate":67,"mana":245,"mana_Growth_Rate":40,"speed":360,"speed_Growth_Rate":0,"range":55,"range_Growth_Rate":0,"attack_Sec":0.87,"attack_Sec_Growth_Rate":0.012,"damage":35,"damage_Growth_Rate":1.5,"damage_Growth_Rate_2":"20% of Magical Power","progression":"None","physical":8,"physical_Growth_Rate":2.2,"magical":30,"magical_Growth_Rate":0,"hp5":6,"hp5_Growth_Rate":0.5,"mp5":4.6,"mp5_Growth_Rate":0.4, "smallimg": "assets/images/god_thumbs/1881.jpg", "physicalprotection": 8, "physicalprotection_Growth_Rate": 2.2, "magicalprotection": 30, "magicalprotection_Growth_Rate": 0}},
{"model": "gods", "data": {"name":"Ra","summary":"","title":"Sun God","pantheon":"Egyptian","type":"RangedMagical","class":"Mage","pros":"High Sustain Pusher","difficulty":"Average","release_date":"May 31 2012","favor":"(Free) 0","gems":"(Free) 0","voicelines":"Ra voicelines","voice_actor":"Chuck Huber","health":385,"health_Growth_Rate":68,"mana":255,"mana_Growth_Rate":48,"speed":350,"speed_Growth_Rate":0,"range":55,"range_Growth_Rate":0,"attack_Sec":0.88,"attack_Sec_Growth_Rate":0.01,"damage":34,"damage_Growth_Rate":1.5,"damage_Growth_Rate_2":"20% of Magical Power","progression":"None","physical":10,"physical_Growth_Rate":2.5,"magical":30,"magical_Growth_Rate":0,"hp5":7,"hp5_Growth_Rate":0.48,"mp5":4.8,"mp5_Growth_Rate":0.44, "smallimg": "assets/images/god_thumbs/T_Ra_Default_Icon.jpg", "physicalprotection": 10, "physicalprotection_Growth_Rate": 2.5, "magicalprotection": 30, "magicalprotection_Growth_Rate": 0}},
{"model": "gods", "data": {"name":"Raijin","summary":"","title":"Master of Thunder","pantheon":"Japanese","type":"RangedMagical","class":"Mage","pros":"Pusher High Mobility","difficulty":"Average","release_date":"February 16 2016","favor":5500,"gems":200,"voicelines":"Raijin voicelines","voice_actor":"","health":385,"health_Growth_Rate":80,"mana":255,"mana_Growth_Rate":43,"speed":355,"speed_Growth_Rate":0,"range":55,"range_Growth_Rate":0,"attack_Sec":0.87,"attack_Sec_Growth_Rate":0.009,"damage":34,"damage_Growth_Rate":1.5,"damage_Growth_Rate_2":"20% of Magical Power","progression":"None","physical":9,"physical_Growth_Rate":3.1,"magical":25,"magical_Growth_Rate":1.25,"hp5":6,"hp5_Growth_Rate":0.45,"mp5":4.6,"mp5_Growth_Rate":0.46, "smallimg": "assets/images/god_thumbs/Raijin_Default_Icon.jpg", "physicalprotection": 9, "physicalprotection_Growth_Rate": 3.1, "magicalprotection": 25, "magicalprotection_Growth_Rate": 1.25}},
{"model": "gods", "data": {"name":"Rama","summary":"","title":"Seventh Avatar of Vishnu","pantheon":"Hindu","type":"RangedPhysical","class":"Hunter","pros":"High Mobility High Attack Speed","difficulty":"Average","release_date":"June 24 2014","favor":5500,"gems":200,"voicelines":"Rama voicelines","voice_actor":"Nick Landis","health":460,"health_Growth_Rate":76,"mana":205,"mana_Growth_Rate":34,"speed":365,"speed_Growth_Rate":0,"range":55,"range_Growth_Rate":0,"attack_Sec":0.95,"attack_Sec_Growth_Rate":0.017,"damage":40,"damage_Growth_Rate":2.5,"damage_Growth_Rate_2":"100% of Physical Power","progression":"None","physical":12,"physical_Growth_Rate":2.8,"magical":30,"magical_Growth_Rate":0.9,"hp5":8,"hp5_Growth_Rate":0.65,"mp5":4.5,"mp5_Growth_Rate":0.25, "smallimg": "assets/images/god_thumbs/2002.jpg", "physicalprotection": 12, "physicalprotection_Growth_Rate": 2.8, "magicalprotection": 30, "magicalprotection_Growth_Rate": 0.9}},
{"model": "gods", "data": {"name":"Ratatoskr","summary":"","title":"The Sly Messenger","pantheon":"Norse","type":"MeleePhysical","class":"Assassin","pros":"Great Jungler High Mobility","difficulty":"Easy","release_date":"June 2 2015","favor":5500,"gems":200,"voicelines":"Ratatoskr voicelines","voice_actor":"Holly Franklin","health":420,"health_Growth_Rate":75,"mana":240,"mana_Growth_Rate":41,"speed":375,"speed_Growth_Rate":0,"range":12,"range_Growth_Rate":0,"attack_Sec":1,"attack_Sec_Growth_Rate":0.02,"damage":39,"damage_Growth_Rate":2.25,"damage_Growth_Rate_2":"100% of Physical Power","progression":"1/0.5/0.5/1.25x damage and swing time hitting in an AoE on the final blow","physical":12,"physical_Growth_Rate":3,"magical":30,"magical_Growth_Rate":0.9,"hp5":9,"hp5_Growth_Rate":0.7,"mp5":4.6,"mp5_Growth_Rate":0.46, "smallimg": "assets/images/god_thumbs/2063.jpg", "physicalprotection": 12, "physicalprotection_Growth_Rate": 3, "magicalprotection": 30, "magicalprotection_Growth_Rate": 0.9}},
{"model": "gods", "data": {"name":"Ravana","summary":"","title":"Demon King of Lanka","pantheon":"Hindu","type":"MeleePhysical","class":"Warrior","pros":"High Single Target Damage High Sustain","difficulty":"Average","release_date":"June 30 2015","favor":5500,"gems":200,"voicelines":"Ravana voicelines","voice_actor":"","health":470,"health_Growth_Rate":82,"mana":230,"mana_Growth_Rate":35,"speed":375,"speed_Growth_Rate":0,"range":12,"range_Growth_Rate":0,"attack_Sec":1,"attack_Sec_Growth_Rate":0.01,"damage":35,"damage_Growth_Rate":2,"damage_Growth_Rate_2":"100% of Physical Power","progression":"0.75/.5/1.25 damage","physical":16,"physical_Growth_Rate":2.9,"magical":30,"magical_Growth_Rate":0.9,"hp5":7,"hp5_Growth_Rate":0.63,"mp5":4.8,"mp5_Growth_Rate":0.4, "smallimg": "assets/images/god_thumbs/Ravana-Default.jpg", "physicalprotection": 16, "physicalprotection_Growth_Rate": 2.9, "magicalprotection": 30, "magicalprotection_Growth_Rate": 0.9}},
{"model": "gods", "data": {"name":"Scylla","summary":"","title":"Horror of the Deep","pantheon":"Greek","type":"RangedMagical","class":"Mage","pros":"High Area Damage","difficulty":"Easy","release_date":"March 5 2014","favor":5500,"gems":200,"voicelines":"Scylla voicelines","voice_actor":"Carrie Savage","health":365,"health_Growth_Rate":68,"mana":298,"mana_Growth_Rate":56,"speed":350,"speed_Growth_Rate":0,"range":55,"range_Growth_Rate":0,"attack_Sec":1,"attack_Sec_Growth_Rate":0.008,"damage":34,"damage_Growth_Rate":1.45,"damage_Growth_Rate_2":"20% of Magical Power","progression":"None","physical":9,"physical_Growth_Rate":2.6,"magical":30,"magical_Growth_Rate":0,"hp5":6,"hp5_Growth_Rate":0.45,"mp5":4.9,"mp5_Growth_Rate":0.4, "smallimg": "assets/images/god_thumbs/1988.jpg", "physicalprotection": 9, "physicalprotection_Growth_Rate": 2.6, "magicalprotection": 30, "magicalprotection_Growth_Rate": 0}},
{"model": "gods", "data": {"name":"Serqet","summary":"","title":"Goddess of Venom","pantheon":"Egyptian","type":"MeleePhysical","class":"Assassin","pros":"High Single Target Damage High Mobility","difficulty":"Average","release_date":"July 15 2014","favor":5500,"gems":200,"voicelines":"Serqet voicelines","voice_actor":"Kristin Sutton","health":400,"health_Growth_Rate":74,"mana":240,"mana_Growth_Rate":40,"speed":370,"speed_Growth_Rate":0,"range":12,"range_Growth_Rate":0,"attack_Sec":1,"attack_Sec_Growth_Rate":0.0216,"damage":39,"damage_Growth_Rate":2.25,"damage_Growth_Rate_2":"100% of Physical Power","progression":"1/.75/1.25x damage","physical":14,"physical_Growth_Rate":2.9,"magical":30,"magical_Growth_Rate":0.9,"hp5":9,"hp5_Growth_Rate":0.7,"mp5":4.3,"mp5_Growth_Rate":0.29, "smallimg": "assets/images/god_thumbs/2005.jpg", "physicalprotection": 14, "physicalprotection_Growth_Rate": 2.9, "magicalprotection": 30, "magicalprotection_Growth_Rate": 0.9}},
{"model": "gods", "data": {"name":"Skadi","summary":"","title":"Goddess of Winter","pantheon":"Norse","type":"RangedPhysical","class":"Hunter","pros":"High Crowd Control Pusher","difficulty":"Hard","release_date":"March 15 2016","favor":11000,"gems":200,"voicelines":"Skadi voicelines","voice_actor":"Martha Harms","health":470,"health_Growth_Rate":78,"mana":220,"mana_Growth_Rate":35,"speed":370,"speed_Growth_Rate":0,"range":55,"range_Growth_Rate":0,"attack_Sec":0.9,"attack_Sec_Growth_Rate":0.016,"damage":35,"damage_Growth_Rate":2.5,"damage_Growth_Rate_2":"100% of Physical Power","progression":"None","physical":11,"physical_Growth_Rate":2.8,"magical":30,"magical_Growth_Rate":0.9,"hp5":8,"hp5_Growth_Rate":0.69,"mp5":4.5,"mp5_Growth_Rate":0.32, "smallimg": "assets/images/god_thumbs/Skadi_mini3.jpg", "physicalprotection": 11, "physicalprotection_Growth_Rate": 2.8, "magicalprotection": 30, "magicalprotection_Growth_Rate": 0.9}},
{"model": "gods", "data": {"name":"Sobek","summary":"","title":"God of the Nile","pantheon":"Egyptian","type":"MeleeMagical","class":"Guardian","pros":"High Crowd Control High Defense","difficulty":"Easy","release_date":"May 31 2012","favor":5500,"gems":200,"voicelines":"Sobek voicelines","voice_actor":"Brandon Potter","health":490,"health_Growth_Rate":81,"mana":210,"mana_Growth_Rate":35,"speed":365,"speed_Growth_Rate":0,"range":12,"range_Growth_Rate":0,"attack_Sec":0.85,"attack_Sec_Growth_Rate":0.014,"damage":38,"damage_Growth_Rate":1.5,"damage_Growth_Rate_2":"20% of Magical Power","progression":"None","physical":19,"physical_Growth_Rate":3,"magical":30,"magical_Growth_Rate":0.9,"hp5":6,"hp5_Growth_Rate":0.75,"mp5":4.5,"mp5_Growth_Rate":0.43, "smallimg": "assets/images/god_thumbs/1747.jpg", "physicalprotection": 19, "physicalprotection_Growth_Rate": 3, "magicalprotection": 30, "magicalprotection_Growth_Rate": 0.9}},
{"model": "gods", "data": {"name":"Sol","summary":"","title":"Goddess of the Sun","pantheon":"Norse","type":"RangedMagical","class":"Mage","pros":"High Single Target Damage High Mobility","difficulty":"Hard","release_date":"October 6 2015","favor":5500,"gems":200,"voicelines":"Sol voicelines","voice_actor":"Jeannie Tirado","health":400,"health_Growth_Rate":75,"mana":300,"mana_Growth_Rate":57,"speed":370,"speed_Growth_Rate":0,"range":55,"range_Growth_Rate":0,"attack_Sec":1,"attack_Sec_Growth_Rate":0.018,"damage":34,"damage_Growth_Rate":1.45,"damage_Growth_Rate_2":"20% of Magical Power","progression":"None","physical":9,"physical_Growth_Rate":2.6,"magical":30,"magical_Growth_Rate":0,"hp5":6,"hp5_Growth_Rate":0.45,"mp5":5,"mp5_Growth_Rate":0.4, "smallimg": "assets/images/god_thumbs/Sol_Default_Icon.png", "physicalprotection": 9, "physicalprotection_Growth_Rate": 2.6, "magicalprotection": 30, "magicalprotection_Growth_Rate": 0}},
{"model": "gods", "data": {"name":"Sun Wukong","summary":"","title":"The Monkey King","pantheon":"Chinese","type":"MeleePhysical","class":"Warrior","pros":"High Defense High Mobility","difficulty":"Average","release_date":"October 23 2013","favor":5500,"gems":200,"voicelines":"Sun Wukong voicelines","voice_actor":"Sean Schemmel","health":470,"health_Growth_Rate":82,"mana":205,"mana_Growth_Rate":35,"speed":375,"speed_Growth_Rate":0,"range":12,"range_Growth_Rate":0,"attack_Sec":1,"attack_Sec_Growth_Rate":0.009,"damage":39,"damage_Growth_Rate":2,"damage_Growth_Rate_2":"100% of Physical Power","progression":"1/.75/1/1.25x damage","physical":18,"physical_Growth_Rate":3,"magical":30,"magical_Growth_Rate":0.9,"hp5":8,"hp5_Growth_Rate":0.8,"mp5":4.3,"mp5_Growth_Rate":0.38, "smallimg": "assets/images/god_thumbs/19441.jpg", "physicalprotection": 18, "physicalprotection_Growth_Rate": 3, "magicalprotection": 30, "magicalprotection_Growth_Rate": 0.9}},
{"model": "gods", "data": {"name":"Sylvanus","summary":"","title":"Keeper of the Wild","pantheon":"Roman","type":"RangedMagical","class":"Guardian","pros":"High Crowd Control High Sustain","difficulty":"Average","release_date":"October 1 2014","favor":5500,"gems":200,"voicelines":"Sylvanus voicelines","voice_actor":"Bob Reed","health":510,"health_Growth_Rate":90,"mana":190,"mana_Growth_Rate":34,"speed":360,"speed_Growth_Rate":0,"range":40,"range_Growth_Rate":0,"attack_Sec":0.8,"attack_Sec_Growth_Rate":0.006,"damage":38,"damage_Growth_Rate":1.5,"damage_Growth_Rate_2":"20% of Magical Power","progression":"None","physical":19,"physical_Growth_Rate":3,"magical":30,"magical_Growth_Rate":0.9,"hp5":8,"hp5_Growth_Rate":0.8,"mp5":4.6,"mp5_Growth_Rate":0.4, "smallimg": "assets/images/god_thumbs/2030.jpg", "physicalprotection": 19, "physicalprotection_Growth_Rate": 3, "magicalprotection": 30, "magicalprotection_Growth_Rate": 0.9}},
{"model": "gods", "data": {"name":"Thanatos","summary":"","title":"Hand of Death","pantheon":"Greek","type":"MeleePhysical","class":"Assassin","pros":"High Sustain","difficulty":"Average","release_date":"September 18 2013","favor":5500,"gems":200,"voicelines":"Thanatos voicelines","voice_actor":"Scott Freeman","health":390,"health_Growth_Rate":75,"mana":240,"mana_Growth_Rate":38,"speed":370,"speed_Growth_Rate":0,"range":12,"range_Growth_Rate":0,"attack_Sec":1,"attack_Sec_Growth_Rate":0.017,"damage":39,"damage_Growth_Rate":2.3,"damage_Growth_Rate_2":"100% of Physical Power","progression":"1/.75/1.5x damage and swing time hitting in an AoE on the final blow","physical":14,"physical_Growth_Rate":2.9,"magical":30,"magical_Growth_Rate":0.9,"hp5":8,"hp5_Growth_Rate":0.67,"mp5":4.4,"mp5_Growth_Rate":0.38, "smallimg": "assets/images/god_thumbs/1943.jpg", "physicalprotection": 14, "physicalprotection_Growth_Rate": 2.9, "magicalprotection": 30, "magicalprotection_Growth_Rate": 0.9}},
{"model": "gods", "data": {"name":"Thor","summary":"","title":"God of Thunder","pantheon":"Norse","type":"MeleePhysical","class":"Assassin","pros":"High Single Target Damage Medium Crowd Control","difficulty":"Hard","release_date":"September 7 2012","favor":"(Free) 0","gems":"(Free) 0","voicelines":"Thor voicelines","voice_actor":"Bruce DuBose","health":475,"health_Growth_Rate":76,"mana":240,"mana_Growth_Rate":38,"speed":370,"speed_Growth_Rate":0,"range":12,"range_Growth_Rate":0,"attack_Sec":1,"attack_Sec_Growth_Rate":0.0145,"damage":39,"damage_Growth_Rate":2.4,"damage_Growth_Rate_2":"100% of Physical Power","progression":"None","physical":14,"physical_Growth_Rate":2.9,"magical":30,"magical_Growth_Rate":0.9,"hp5":9,"hp5_Growth_Rate":0.69,"mp5":4.4,"mp5_Growth_Rate":0.29, "smallimg": "assets/images/god_thumbs/1779.jpg", "physicalprotection": 14, "physicalprotection_Growth_Rate": 2.9, "magicalprotection": 30, "magicalprotection_Growth_Rate": 0.9}},
{"model": "gods", "data": {"name":"Tyr","summary":"","title":"The Lawgiver","pantheon":"Norse","type":"MeleePhysical","class":"Warrior","pros":"High Defense Medium Crowd Control","difficulty":"Hard","release_date":"August 7 2013","favor":5500,"gems":200,"voicelines":"Tyr voicelines","voice_actor":"Ian Sinclair","health":475,"health_Growth_Rate":80,"mana":230,"mana_Growth_Rate":40,"speed":375,"speed_Growth_Rate":0,"range":12,"range_Growth_Rate":0,"attack_Sec":1,"attack_Sec_Growth_Rate":0.009,"damage":39,"damage_Growth_Rate":2,"damage_Growth_Rate_2":"100% of Physical Power","progression":"1/.5/1.5x damage","physical":15,"physical_Growth_Rate":3,"magical":30,"magical_Growth_Rate":0.9,"hp5":8,"hp5_Growth_Rate":0.72,"mp5":4.4,"mp5_Growth_Rate":0.29, "smallimg": "assets/images/god_thumbs/1924.jpg", "physicalprotection": 15, "physicalprotection_Growth_Rate": 3, "magicalprotection": 30, "magicalprotection_Growth_Rate": 0.9}},
{"model": "gods", "data": {"name":"Ullr","summary":"","title":"The Glorious One","pantheon":"Norse","type":"RangedPhysical","class":"Hunter","pros":"High Sustain","difficulty":"Hard","release_date":"March 19 2014","favor":5500,"gems":200,"voicelines":"Ullr voicelines","voice_actor":"Bill Jenkins","health":480,"health_Growth_Rate":80,"mana":230,"mana_Growth_Rate":40,"speed":360,"speed_Growth_Rate":0,"range":55,"range_Growth_Rate":0,"attack_Sec":0.95,"attack_Sec_Growth_Rate":0.015,"damage":38,"damage_Growth_Rate":2.4,"damage_Growth_Rate_2":"100% of Physical Power","progression":"None","physical":13,"physical_Growth_Rate":3,"magical":30,"magical_Growth_Rate":0.9,"hp5":8,"hp5_Growth_Rate":0.71,"mp5":4.4,"mp5_Growth_Rate":0.38, "smallimg": "assets/images/god_thumbs/1991.jpg", "physicalprotection": 13, "physicalprotection_Growth_Rate": 3, "magicalprotection": 30, "magicalprotection_Growth_Rate": 0.9}},
{"model": "gods", "data": {"name":"Vamana","summary":"","title":"Fifth Avatar of Vishnu","pantheon":"Hindu","type":"MeleePhysical","class":"Warrior","pros":"High Defense High Sustain","difficulty":"Average","release_date":"May 31 2012","favor":5500,"gems":200,"voicelines":"Vamana voicelines","voice_actor":"Todd Haberkorn","health":480,"health_Growth_Rate":85,"mana":200,"mana_Growth_Rate":39,"speed":380,"speed_Growth_Rate":0,"range":12,"range_Growth_Rate":0,"attack_Sec":0.9,"attack_Sec_Growth_Rate":0.014,"damage":37,"damage_Growth_Rate":2,"damage_Growth_Rate_2":"100% of Physical Power","progression":"None","physical":18,"physical_Growth_Rate":2.9,"magical":30,"magical_Growth_Rate":0.9,"hp5":8,"hp5_Growth_Rate":0.5,"mp5":4.7,"mp5_Growth_Rate":0.41, "smallimg": "assets/images/god_thumbs/1723.jpg", "physicalprotection": 18, "physicalprotection_Growth_Rate": 2.9, "magicalprotection": 30, "magicalprotection_Growth_Rate": 0.9}},
{"model": "gods", "data": {"name":"Vulcan","summary":"","title":"Smith of the Gods","pantheon":"Roman","type":"RangedMagical","class":"Mage","pros":"Pusher High Area Damage","difficulty":"Average","release_date":"January 31 2013","favor":5500,"gems":200,"voicelines":"Vulcan voicelines","voice_actor":"Rick Robertson","health":380,"health_Growth_Rate":71,"mana":245,"mana_Growth_Rate":40,"speed":360,"speed_Growth_Rate":0,"range":55,"range_Growth_Rate":0,"attack_Sec":0.9,"attack_Sec_Growth_Rate":0.011,"damage":34,"damage_Growth_Rate":1.5,"damage_Growth_Rate_2":"20% of Magical Power","progression":"None","physical":13,"physical_Growth_Rate":3,"magical":30,"magical_Growth_Rate":0,"hp5":7,"hp5_Growth_Rate":0.48,"mp5":4.8,"mp5_Growth_Rate":0.45, "smallimg": "assets/images/god_thumbs/1869.jpg", "physicalprotection": 13, "physicalprotection_Growth_Rate": 3, "magicalprotection": 30, "magicalprotection_Growth_Rate": 0}},
{"model": "gods", "data": {"name":"Xbalanque","summary":"","title":"Hidden Jaguar Sun","pantheon":"Mayan","type":"RangedPhysical","class":"Hunter","pros":"High Single Target Damage Medium Area Damage","difficulty":"Average","release_date":"December 21 2012","favor":5500,"gems":200,"voicelines":"Xbalanque voicelines","voice_actor":"Josh Grelle","health":455,"health_Growth_Rate":75,"mana":220,"mana_Growth_Rate":37,"speed":365,"speed_Growth_Rate":0,"range":55,"range_Growth_Rate":0,"attack_Sec":0.95,"attack_Sec_Growth_Rate":0.01,"damage":37,"damage_Growth_Rate":2.5,"damage_Growth_Rate_2":"100% of Physical Power","progression":"None","physical":12,"physical_Growth_Rate":2.9,"magical":30,"magical_Growth_Rate":0.9,"hp5":8,"hp5_Growth_Rate":0.68,"mp5":4.4,"mp5_Growth_Rate":0.4, "smallimg": "assets/images/god_thumbs/standardxbalanque.jpg", "physicalprotection": 12, "physicalprotection_Growth_Rate": 2.9, "magicalprotection": 30, "magicalprotection_Growth_Rate": 0.9}},
{"model": "gods", "data": {"name":"Xing Tian","summary":"","title":"The Relentless","pantheon":"Chinese","type":"MeleeMagical","class":"Guardian","pros":"High Crowd Control","difficulty":"Average","release_date":"September 1 2015","favor":5500,"gems":200,"voicelines":"Xing Tian voicelines","voice_actor":"","health":485,"health_Growth_Rate":90,"mana":200,"mana_Growth_Rate":40,"speed":360,"speed_Growth_Rate":0,"range":12,"range_Growth_Rate":0,"attack_Sec":0.9,"attack_Sec_Growth_Rate":0.012,"damage":35,"damage_Growth_Rate":1.55,"damage_Growth_Rate_2":"20% of Magical Power","progression":"1/1/1/1x damage and swing time","physical":21,"physical_Growth_Rate":3.4,"magical":30,"magical_Growth_Rate":0.9,"hp5":5,"hp5_Growth_Rate":0.54,"mp5":5,"mp5_Growth_Rate":0.45, "smallimg": "assets/images/god_thumbs/T_XingTian_Default_Icon.png", "physicalprotection": 21, "physicalprotection_Growth_Rate": 3.4, "magicalprotection": 30, "magicalprotection_Growth_Rate": 0.9}},
{"model": "gods", "data": {"name":"Ymir","summary":"","title":"Father of the Frost Giants","pantheon":"Norse","type":"MeleeMagical","class":"Guardian","pros":"High Crowd Control High Defense","difficulty":"Easy","release_date":"May 31 2012","favor":"(Free) 0","gems":"(Free) 0","voicelines":"Ymir voicelines","voice_actor":"Charles Campbell","health":510,"health_Growth_Rate":104,"mana":200,"mana_Growth_Rate":32,"speed":360,"speed_Growth_Rate":0,"range":12,"range_Growth_Rate":0,"attack_Sec":0.85,"attack_Sec_Growth_Rate":0.012,"damage":38,"damage_Growth_Rate":1.55,"damage_Growth_Rate_2":"20% of Magical Power","progression":"None","physical":23,"physical_Growth_Rate":3.3,"magical":30,"magical_Growth_Rate":0.9,"hp5":8,"hp5_Growth_Rate":0.9,"mp5":4.5,"mp5_Growth_Rate":0.4, "smallimg": "assets/images/god_thumbs/1670.jpg", "physicalprotection": 23, "physicalprotection_Growth_Rate": 3.3, "magicalprotection": 30, "magicalprotection_Growth_Rate": 0.9}},
{"model": "gods", "data": {"name":"Zeus","summary":"","title":"God of the Sky","pantheon":"Greek","type":"RangedMagical","class":"Mage","pros":"High Area Damage","difficulty":"Average","release_date":"May 31 2012","favor":5500,"gems":200,"voicelines":"Zeus voicelines","voice_actor":"Christopher Sabat","health":380,"health_Growth_Rate":71,"mana":245,"mana_Growth_Rate":44,"speed":355,"speed_Growth_Rate":0,"range":55,"range_Growth_Rate":0,"attack_Sec":0.87,"attack_Sec_Growth_Rate":0.0099,"damage":35,"damage_Growth_Rate":1.5,"damage_Growth_Rate_2":"20% of Magical Power","progression":"None","physical":8,"physical_Growth_Rate":2.7,"magical":30,"magical_Growth_Rate":0,"hp5":6,"hp5_Growth_Rate":0.45,"mp5":4.6,"mp5_Growth_Rate":0.45, "smallimg": "assets/images/god_thumbs/1672.jpg", "physicalprotection": 8, "physicalprotection_Growth_Rate": 2.7, "magicalprotection": 30, "magicalprotection_Growth_Rate": 0}},
{"model": "gods", "data": {"name":"Zhong Kui","summary":"","title":"The Demon Queller","pantheon":"Chinese","type":"RangedMagical","class":"Mage","pros":"Medium Crowd Control High Area Damage","difficulty":"Easy","release_date":"August 28 2013","favor":5500,"gems":200,"voicelines":"Zhong Kui voicelines","voice_actor":"Daniel Penz","health":450,"health_Growth_Rate":85,"mana":250,"mana_Growth_Rate":47,"speed":360,"speed_Growth_Rate":0,"range":55,"range_Growth_Rate":0,"attack_Sec":0.86,"attack_Sec_Growth_Rate":0.01,"damage":33,"damage_Growth_Rate":1.5,"damage_Growth_Rate_2":"20% of Magical Power","progression":"None","physical":8,"physical_Growth_Rate":2.6,"magical":30,"magical_Growth_Rate":0.9,"hp5":6,"hp5_Growth_Rate":0.44,"mp5":4.8,"mp5_Growth_Rate":0.45, "smallimg": "assets/images/god_thumbs/1926.jpg", "physicalprotection": 8, "physicalprotection_Growth_Rate": 2.6, "magicalprotection": 30, "magicalprotection_Growth_Rate": 0.9}}]